cont/__main__.py
cont/info.py
cont/setup.py
cont/version.py
tests/test_version.py
cont-0.0.1.dist-info/LICENSE
cont-0.0.1.dist-info/METADATA
cont-0.0.1.dist-info/WHEEL
cont-0.0.1.dist-info/entry_points.txt
cont-0.0.1.dist-info/top_level.txt
cont-0.0.1.dist-info/RECORD
