Metadata-Version: 2.1
Name: cont
Version: 0.0.1
Summary: Utility to manage containers
Home-page: https://github.com/joaompinto/osandbox/cont
Author: João Pinto
Author-email: lamego.pinto@gmail.com
License: MIT
Platform: UNKNOWN
License-File: LICENSE
Requires-Dist: docopt
